{
  "base": "USD",
  "last_updated": "2026-05-29T17:53:52Z",
  "currencies": [
    {
      "code": "AED",
      "rate": 3.67315,
      "name": "United Arab Emirates Dirham"
    },
    {
      "code": "AFN",
      "rate": 62.999998,
      "name": "Afghan Afghani"
    },
    {
      "code": "ALL",
      "rate": 82.006217,
      "name": "Albanian Lek"
    },
    {
      "code": "AMD",
      "rate": 368.18,
      "name": "Armenian Dram"
    },
    {
      "code": "ANG",
      "rate": 1.79,
      "name": "Netherlands Antillean Guilder"
    },
    {
      "code": "AOA",
      "rate": 913.116,
      "name": "Angolan Kwanza"
    },
    {
      "code": "ARS",
      "rate": 1409.7405,
      "name": "Argentine Peso"
    },
    {
      "code": "AUD",
      "rate": 1.390998,
      "name": "Australian Dollar"
    },
    {
      "code": "AWG",
      "rate": 1.8025,
      "name": "Aruban Florin"
    },
    {
      "code": "AZN",
      "rate": 1.7,
      "name": "Azerbaijani Manat"
    },
    {
      "code": "BAM",
      "rate": 1.679981,
      "name": "Bosnia-Herzegovina Convertible Mark"
    },
    {
      "code": "BBD",
      "rate": 2,
      "name": "Barbadian Dollar"
    },
    {
      "code": "BDT",
      "rate": 122.760854,
      "name": "Bangladeshi Taka"
    },
    {
      "code": "BGN",
      "rate": 1.675786,
      "name": "Bulgarian Lev"
    },
    {
      "code": "BHD",
      "rate": 0.377261,
      "name": "Bahraini Dinar"
    },
    {
      "code": "BIF",
      "rate": 2968.873113,
      "name": "Burundian Franc"
    },
    {
      "code": "BMD",
      "rate": 1,
      "name": "Bermudan Dollar"
    },
    {
      "code": "BND",
      "rate": 1.278067,
      "name": "Brunei Dollar"
    },
    {
      "code": "BOB",
      "rate": 6.910443,
      "name": "Bolivian Boliviano"
    },
    {
      "code": "BRL",
      "rate": 5.063484,
      "name": "Brazilian Real"
    },
    {
      "code": "BSD",
      "rate": 1,
      "name": "Bahamian Dollar"
    },
    {
      "code": "BTC",
      "rate": 0.000013520281,
      "name": "Bitcoin"
    },
    {
      "code": "BTN",
      "rate": 94.95953,
      "name": "Bhutanese Ngultrum"
    },
    {
      "code": "BWP",
      "rate": 13.418887,
      "name": "Botswanan Pula"
    },
    {
      "code": "BYN",
      "rate": 2.740298,
      "name": "Belarusian Ruble"
    },
    {
      "code": "BZD",
      "rate": 2.011459,
      "name": "Belize Dollar"
    },
    {
      "code": "CAD",
      "rate": 1.379935,
      "name": "Canadian Dollar"
    },
    {
      "code": "CDF",
      "rate": 2303.949421,
      "name": "Congolese Franc"
    },
    {
      "code": "CHF",
      "rate": 0.781353,
      "name": "Swiss Franc"
    },
    {
      "code": "CLF",
      "rate": 0.022637,
      "name": "Chilean Unit of Account (UF)"
    },
    {
      "code": "CLP",
      "rate": 890.91,
      "name": "Chilean Peso"
    },
    {
      "code": "CNH",
      "rate": 6.763424,
      "name": "Chinese Yuan (Offshore)"
    },
    {
      "code": "CNY",
      "rate": 6.7797,
      "name": "Chinese Yuan"
    },
    {
      "code": "COP",
      "rate": 3689.11,
      "name": "Colombian Peso"
    },
    {
      "code": "CRC",
      "rate": 452.063886,
      "name": "Costa Rican Colón"
    },
    {
      "code": "CUC",
      "rate": 1,
      "name": "Cuban Convertible Peso"
    },
    {
      "code": "CUP",
      "rate": 25.75,
      "name": "Cuban Peso"
    },
    {
      "code": "CVE",
      "rate": 94.713111,
      "name": "Cape Verdean Escudo"
    },
    {
      "code": "CZK",
      "rate": 20.8076,
      "name": "Czech Republic Koruna"
    },
    {
      "code": "DJF",
      "rate": 178.099632,
      "name": "Djiboutian Franc"
    },
    {
      "code": "DKK",
      "rate": 6.40328,
      "name": "Danish Krone"
    },
    {
      "code": "DOP",
      "rate": 58.753799,
      "name": "Dominican Peso"
    },
    {
      "code": "DZD",
      "rate": 132.51169,
      "name": "Algerian Dinar"
    },
    {
      "code": "EGP",
      "rate": 52.2127,
      "name": "Egyptian Pound"
    },
    {
      "code": "ERN",
      "rate": 15,
      "name": "Eritrean Nakfa"
    },
    {
      "code": "ETB",
      "rate": 161.246793,
      "name": "Ethiopian Birr"
    },
    {
      "code": "EUR",
      "rate": 0.856738,
      "name": "Euro"
    },
    {
      "code": "FJD",
      "rate": 2.2218,
      "name": "Fijian Dollar"
    },
    {
      "code": "FKP",
      "rate": 0.742543,
      "name": "Falkland Islands Pound"
    },
    {
      "code": "GBP",
      "rate": 0.742543,
      "name": "British Pound Sterling"
    },
    {
      "code": "GEL",
      "rate": 2.66,
      "name": "Georgian Lari"
    },
    {
      "code": "GGP",
      "rate": 0.742543,
      "name": "Guernsey Pound"
    },
    {
      "code": "GHS",
      "rate": 10.7037,
      "name": "Ghanaian Cedi"
    },
    {
      "code": "GIP",
      "rate": 0.742543,
      "name": "Gibraltar Pound"
    },
    {
      "code": "GMD",
      "rate": 73.000001,
      "name": "Gambian Dalasi"
    },
    {
      "code": "GNF",
      "rate": 8766.500273,
      "name": "Guinean Franc"
    },
    {
      "code": "GTQ",
      "rate": 7.628513,
      "name": "Guatemalan Quetzal"
    },
    {
      "code": "GYD",
      "rate": 209.220177,
      "name": "Guyanaese Dollar"
    },
    {
      "code": "HKD",
      "rate": 7.837017,
      "name": "Hong Kong Dollar"
    },
    {
      "code": "HNL",
      "rate": 26.6153,
      "name": "Honduran Lempira"
    },
    {
      "code": "HRK",
      "rate": 6.455676,
      "name": "Croatian Kuna"
    },
    {
      "code": "HTG",
      "rate": 130.9677,
      "name": "Haitian Gourde"
    },
    {
      "code": "HUF",
      "rate": 302.894377,
      "name": "Hungarian Forint"
    },
    {
      "code": "IDR",
      "rate": 17804.84308,
      "name": "Indonesian Rupiah"
    },
    {
      "code": "ILS",
      "rate": 2.80185,
      "name": "Israeli New Sheqel"
    },
    {
      "code": "IMP",
      "rate": 0.742543,
      "name": "Manx pound"
    },
    {
      "code": "INR",
      "rate": 94.877248,
      "name": "Indian Rupee"
    },
    {
      "code": "IQD",
      "rate": 1310.194333,
      "name": "Iraqi Dinar"
    },
    {
      "code": "IRR",
      "rate": 1342125,
      "name": "Iranian Rial"
    },
    {
      "code": "ISK",
      "rate": 122.87,
      "name": "Icelandic Króna"
    },
    {
      "code": "JEP",
      "rate": 0.742543,
      "name": "Jersey Pound"
    },
    {
      "code": "JMD",
      "rate": 157.513855,
      "name": "Jamaican Dollar"
    },
    {
      "code": "JOD",
      "rate": 0.709,
      "name": "Jordanian Dinar"
    },
    {
      "code": "JPY",
      "rate": 159.19841667,
      "name": "Japanese Yen"
    },
    {
      "code": "KES",
      "rate": 129.46,
      "name": "Kenyan Shilling"
    },
    {
      "code": "KGS",
      "rate": 87.45,
      "name": "Kyrgystani Som"
    },
    {
      "code": "KHR",
      "rate": 4016.545226,
      "name": "Cambodian Riel"
    },
    {
      "code": "KMF",
      "rate": 422.999947,
      "name": "Comorian Franc"
    },
    {
      "code": "KPW",
      "rate": 900,
      "name": "North Korean Won"
    },
    {
      "code": "KRW",
      "rate": 1504.430934,
      "name": "South Korean Won"
    },
    {
      "code": "KWD",
      "rate": 0.309416,
      "name": "Kuwaiti Dinar"
    },
    {
      "code": "KYD",
      "rate": 0.833462,
      "name": "Cayman Islands Dollar"
    },
    {
      "code": "KZT",
      "rate": 487.321617,
      "name": "Kazakhstani Tenge"
    },
    {
      "code": "LAK",
      "rate": 21957.744341,
      "name": "Laotian Kip"
    },
    {
      "code": "LBP",
      "rate": 89337.6398,
      "name": "Lebanese Pound"
    },
    {
      "code": "LKR",
      "rate": 330.034837,
      "name": "Sri Lankan Rupee"
    },
    {
      "code": "LRD",
      "rate": 183.005641,
      "name": "Liberian Dollar"
    },
    {
      "code": "LSL",
      "rate": 16.244423,
      "name": "Lesotho Loti"
    },
    {
      "code": "LYD",
      "rate": 6.350202,
      "name": "Libyan Dinar"
    },
    {
      "code": "MAD",
      "rate": 9.19318,
      "name": "Moroccan Dirham"
    },
    {
      "code": "MDL",
      "rate": 17.248908,
      "name": "Moldovan Leu"
    },
    {
      "code": "MGA",
      "rate": 4190.067838,
      "name": "Malagasy Ariary"
    },
    {
      "code": "MKD",
      "rate": 52.804501,
      "name": "Macedonian Denar"
    },
    {
      "code": "MMK",
      "rate": 2099.81,
      "name": "Myanma Kyat"
    },
    {
      "code": "MNT",
      "rate": 3569.47,
      "name": "Mongolian Tugrik"
    },
    {
      "code": "MOP",
      "rate": 8.070537,
      "name": "Macanese Pataca"
    },
    {
      "code": "MRU",
      "rate": 40.00378,
      "name": "Mauritanian Ouguiya"
    },
    {
      "code": "MUR",
      "rate": 47.369999,
      "name": "Mauritian Rupee"
    },
    {
      "code": "MVR",
      "rate": 15.41,
      "name": "Maldivian Rufiyaa"
    },
    {
      "code": "MWK",
      "rate": 1734.17902,
      "name": "Malawian Kwacha"
    },
    {
      "code": "MXN",
      "rate": 17.34109,
      "name": "Mexican Peso"
    },
    {
      "code": "MYR",
      "rate": 3.965,
      "name": "Malaysian Ringgit"
    },
    {
      "code": "MZN",
      "rate": 63.904994,
      "name": "Mozambican Metical"
    },
    {
      "code": "NAD",
      "rate": 16.24491,
      "name": "Namibian Dollar"
    },
    {
      "code": "NGN",
      "rate": 1372.17,
      "name": "Nigerian Naira"
    },
    {
      "code": "NIO",
      "rate": 36.805916,
      "name": "Nicaraguan Córdoba"
    },
    {
      "code": "NOK",
      "rate": 9.24506,
      "name": "Norwegian Krone"
    },
    {
      "code": "NPR",
      "rate": 152.99664,
      "name": "Nepalese Rupee"
    },
    {
      "code": "NZD",
      "rate": 1.669533,
      "name": "New Zealand Dollar"
    },
    {
      "code": "OMR",
      "rate": 0.384502,
      "name": "Omani Rial"
    },
    {
      "code": "PAB",
      "rate": 1,
      "name": "Panamanian Balboa"
    },
    {
      "code": "PEN",
      "rate": 3.399286,
      "name": "Peruvian Nuevo Sol"
    },
    {
      "code": "PGK",
      "rate": 4.367807,
      "name": "Papua New Guinean Kina"
    },
    {
      "code": "PHP",
      "rate": 61.492007,
      "name": "Philippine Peso"
    },
    {
      "code": "PKR",
      "rate": 278.456696,
      "name": "Pakistani Rupee"
    },
    {
      "code": "PLN",
      "rate": 3.623592,
      "name": "Polish Zloty"
    },
    {
      "code": "PYG",
      "rate": 6017.113499,
      "name": "Paraguayan Guarani"
    },
    {
      "code": "QAR",
      "rate": 3.645555,
      "name": "Qatari Rial"
    },
    {
      "code": "RON",
      "rate": 4.4996,
      "name": "Romanian Leu"
    },
    {
      "code": "RSD",
      "rate": 100.605,
      "name": "Serbian Dinar"
    },
    {
      "code": "RUB",
      "rate": 70.996323,
      "name": "Russian Ruble"
    },
    {
      "code": "RWF",
      "rate": 1467.639593,
      "name": "Rwandan Franc"
    },
    {
      "code": "SAR",
      "rate": 3.759403,
      "name": "Saudi Riyal"
    },
    {
      "code": "SBD",
      "rate": 8.032647,
      "name": "Solomon Islands Dollar"
    },
    {
      "code": "SCR",
      "rate": 13.645083,
      "name": "Seychellois Rupee"
    },
    {
      "code": "SDG",
      "rate": 600.5,
      "name": "Sudanese Pound"
    },
    {
      "code": "SEK",
      "rate": 9.2173,
      "name": "Swedish Krona"
    },
    {
      "code": "SGD",
      "rate": 1.275829,
      "name": "Singapore Dollar"
    },
    {
      "code": "SHP",
      "rate": 0.742543,
      "name": "Saint Helena Pound"
    },
    {
      "code": "SLE",
      "rate": 24.625,
      "name": "Sierra Leonean Leone"
    },
    {
      "code": "SLL",
      "rate": 20969.5,
      "name": "Sierra Leonean Leone (Old)"
    },
    {
      "code": "SOS",
      "rate": 571.561111,
      "name": "Somali Shilling"
    },
    {
      "code": "SRD",
      "rate": 37.1705,
      "name": "Surinamese Dollar"
    },
    {
      "code": "SSP",
      "rate": 130.26,
      "name": "South Sudanese Pound"
    },
    {
      "code": "STD",
      "rate": 22281.8,
      "name": "São Tomé and Príncipe Dobra (pre-2018)"
    },
    {
      "code": "STN",
      "rate": 21.044223,
      "name": "São Tomé and Príncipe Dobra"
    },
    {
      "code": "SVC",
      "rate": 8.751074,
      "name": "Salvadoran Colón"
    },
    {
      "code": "SYP",
      "rate": 13002,
      "name": "Syrian Pound"
    },
    {
      "code": "SZL",
      "rate": 16.239687,
      "name": "Swazi Lilangeni"
    },
    {
      "code": "THB",
      "rate": 32.497,
      "name": "Thai Baht"
    },
    {
      "code": "TJS",
      "rate": 9.231047,
      "name": "Tajikistani Somoni"
    },
    {
      "code": "TMT",
      "rate": 3.51,
      "name": "Turkmenistani Manat"
    },
    {
      "code": "TND",
      "rate": 2.924805,
      "name": "Tunisian Dinar"
    },
    {
      "code": "TOP",
      "rate": 2.40776,
      "name": "Tongan Pa'anga"
    },
    {
      "code": "TRY",
      "rate": 45.898202,
      "name": "Turkish Lira"
    },
    {
      "code": "TTD",
      "rate": 6.793623,
      "name": "Trinidad and Tobago Dollar"
    },
    {
      "code": "TWD",
      "rate": 31.381503,
      "name": "New Taiwan Dollar"
    },
    {
      "code": "TZS",
      "rate": 2629.933,
      "name": "Tanzanian Shilling"
    },
    {
      "code": "UAH",
      "rate": 44.293078,
      "name": "Ukrainian Hryvnia"
    },
    {
      "code": "UGX",
      "rate": 3769.889192,
      "name": "Ugandan Shilling"
    },
    {
      "code": "USD",
      "rate": 1,
      "name": "United States Dollar"
    },
    {
      "code": "UYU",
      "rate": 40.150739,
      "name": "Uruguayan Peso"
    },
    {
      "code": "UZS",
      "rate": 12006.346485,
      "name": "Uzbekistan Som"
    },
    {
      "code": "VES",
      "rate": 543.903368,
      "name": "Venezuelan Bolívar Soberano"
    },
    {
      "code": "VND",
      "rate": 26312.327781,
      "name": "Vietnamese Dong"
    },
    {
      "code": "VUV",
      "rate": 119.389,
      "name": "Vanuatu Vatu"
    },
    {
      "code": "WST",
      "rate": 2.74422,
      "name": "Samoan Tala"
    },
    {
      "code": "YER",
      "rate": 238.649953,
      "name": "Yemeni Rial"
    },
    {
      "code": "ZAR",
      "rate": 16.209167,
      "name": "South African Rand"
    },
    {
      "code": "ZMW",
      "rate": 18.451265,
      "name": "Zambian Kwacha"
    },
    {
      "code": "ZWG",
      "rate": 25.3626,
      "name": "Zimbabwean ZiG"
    },
    {
      "code": "ZWL",
      "rate": 322,
      "name": "Zimbabwean Dollar"
    }
  ]
}
