{
  "base": "USD",
  "last_updated": "2026-06-30T13:22:45Z",
  "currencies": [
    {
      "code": "AED",
      "rate": 3.6725,
      "name": "United Arab Emirates Dirham"
    },
    {
      "code": "AFN",
      "rate": 63.999997,
      "name": "Afghan Afghani"
    },
    {
      "code": "ALL",
      "rate": 82.446916,
      "name": "Albanian Lek"
    },
    {
      "code": "AMD",
      "rate": 368.204619,
      "name": "Armenian Dram"
    },
    {
      "code": "ANG",
      "rate": 1.79,
      "name": "Netherlands Antillean Guilder"
    },
    {
      "code": "AOA",
      "rate": 912.57,
      "name": "Angolan Kwanza"
    },
    {
      "code": "ARS",
      "rate": 1481.2508,
      "name": "Argentine Peso"
    },
    {
      "code": "AUD",
      "rate": 1.452454,
      "name": "Australian Dollar"
    },
    {
      "code": "AWG",
      "rate": 1.8,
      "name": "Aruban Florin"
    },
    {
      "code": "AZN",
      "rate": 1.7,
      "name": "Azerbaijani Manat"
    },
    {
      "code": "BAM",
      "rate": 1.715719,
      "name": "Bosnia-Herzegovina Convertible Mark"
    },
    {
      "code": "BBD",
      "rate": 2,
      "name": "Barbadian Dollar"
    },
    {
      "code": "BDT",
      "rate": 123.237271,
      "name": "Bangladeshi Taka"
    },
    {
      "code": "BGN",
      "rate": 1.715745,
      "name": "Bulgarian Lev"
    },
    {
      "code": "BHD",
      "rate": 0.377133,
      "name": "Bahraini Dinar"
    },
    {
      "code": "BIF",
      "rate": 2976.653237,
      "name": "Burundian Franc"
    },
    {
      "code": "BMD",
      "rate": 1,
      "name": "Bermudan Dollar"
    },
    {
      "code": "BND",
      "rate": 1.294833,
      "name": "Brunei Dollar"
    },
    {
      "code": "BOB",
      "rate": 6.927015,
      "name": "Bolivian Boliviano"
    },
    {
      "code": "BRL",
      "rate": 5.2023,
      "name": "Brazilian Real"
    },
    {
      "code": "BSD",
      "rate": 1,
      "name": "Bahamian Dollar"
    },
    {
      "code": "BTC",
      "rate": 0.000017115671,
      "name": "Bitcoin"
    },
    {
      "code": "BTN",
      "rate": 94.645256,
      "name": "Bhutanese Ngultrum"
    },
    {
      "code": "BWP",
      "rate": 13.556631,
      "name": "Botswanan Pula"
    },
    {
      "code": "BYN",
      "rate": 2.903787,
      "name": "Belarusian Ruble"
    },
    {
      "code": "BZD",
      "rate": 2.011641,
      "name": "Belize Dollar"
    },
    {
      "code": "CAD",
      "rate": 1.422782,
      "name": "Canadian Dollar"
    },
    {
      "code": "CDF",
      "rate": 2314.085243,
      "name": "Congolese Franc"
    },
    {
      "code": "CHF",
      "rate": 0.809212,
      "name": "Swiss Franc"
    },
    {
      "code": "CLF",
      "rate": 0.023401,
      "name": "Chilean Unit of Account (UF)"
    },
    {
      "code": "CLP",
      "rate": 920.93,
      "name": "Chilean Peso"
    },
    {
      "code": "CNH",
      "rate": 6.792613,
      "name": "Chinese Yuan (Offshore)"
    },
    {
      "code": "CNY",
      "rate": 6.794,
      "name": "Chinese Yuan"
    },
    {
      "code": "COP",
      "rate": 3452.84,
      "name": "Colombian Peso"
    },
    {
      "code": "CRC",
      "rate": 454.166354,
      "name": "Costa Rican Colón"
    },
    {
      "code": "CUC",
      "rate": 1,
      "name": "Cuban Convertible Peso"
    },
    {
      "code": "CUP",
      "rate": 25.75,
      "name": "Cuban Peso"
    },
    {
      "code": "CVE",
      "rate": 96.734271,
      "name": "Cape Verdean Escudo"
    },
    {
      "code": "CZK",
      "rate": 21.2759,
      "name": "Czech Republic Koruna"
    },
    {
      "code": "DJF",
      "rate": 178.123233,
      "name": "Djiboutian Franc"
    },
    {
      "code": "DKK",
      "rate": 6.558807,
      "name": "Danish Krone"
    },
    {
      "code": "DOP",
      "rate": 59.62725,
      "name": "Dominican Peso"
    },
    {
      "code": "DZD",
      "rate": 133.330695,
      "name": "Algerian Dinar"
    },
    {
      "code": "EGP",
      "rate": 49.2302,
      "name": "Egyptian Pound"
    },
    {
      "code": "ERN",
      "rate": 15,
      "name": "Eritrean Nakfa"
    },
    {
      "code": "ETB",
      "rate": 160.107489,
      "name": "Ethiopian Birr"
    },
    {
      "code": "EUR",
      "rate": 0.87748,
      "name": "Euro"
    },
    {
      "code": "FJD",
      "rate": 2.24725,
      "name": "Fijian Dollar"
    },
    {
      "code": "FKP",
      "rate": 0.756672,
      "name": "Falkland Islands Pound"
    },
    {
      "code": "GBP",
      "rate": 0.756672,
      "name": "British Pound Sterling"
    },
    {
      "code": "GEL",
      "rate": 2.64,
      "name": "Georgian Lari"
    },
    {
      "code": "GGP",
      "rate": 0.756672,
      "name": "Guernsey Pound"
    },
    {
      "code": "GHS",
      "rate": 11.325109,
      "name": "Ghanaian Cedi"
    },
    {
      "code": "GIP",
      "rate": 0.756672,
      "name": "Gibraltar Pound"
    },
    {
      "code": "GMD",
      "rate": 73.500003,
      "name": "Gambian Dalasi"
    },
    {
      "code": "GNF",
      "rate": 8768.360484,
      "name": "Guinean Franc"
    },
    {
      "code": "GTQ",
      "rate": 7.631137,
      "name": "Guatemalan Quetzal"
    },
    {
      "code": "GYD",
      "rate": 209.23162,
      "name": "Guyanaese Dollar"
    },
    {
      "code": "HKD",
      "rate": 7.841976,
      "name": "Hong Kong Dollar"
    },
    {
      "code": "HNL",
      "rate": 26.765153,
      "name": "Honduran Lempira"
    },
    {
      "code": "HRK",
      "rate": 6.609706,
      "name": "Croatian Kuna"
    },
    {
      "code": "HTG",
      "rate": 130.78168,
      "name": "Haitian Gourde"
    },
    {
      "code": "HUF",
      "rate": 312.597164,
      "name": "Hungarian Forint"
    },
    {
      "code": "IDR",
      "rate": 17917.969077,
      "name": "Indonesian Rupiah"
    },
    {
      "code": "ILS",
      "rate": 2.9795,
      "name": "Israeli New Sheqel"
    },
    {
      "code": "IMP",
      "rate": 0.756672,
      "name": "Manx pound"
    },
    {
      "code": "INR",
      "rate": 94.629756,
      "name": "Indian Rupee"
    },
    {
      "code": "IQD",
      "rate": 1310.362217,
      "name": "Iraqi Dinar"
    },
    {
      "code": "IRR",
      "rate": 1375250,
      "name": "Iranian Rial"
    },
    {
      "code": "ISK",
      "rate": 126.36,
      "name": "Icelandic Króna"
    },
    {
      "code": "JEP",
      "rate": 0.756672,
      "name": "Jersey Pound"
    },
    {
      "code": "JMD",
      "rate": 157.59739,
      "name": "Jamaican Dollar"
    },
    {
      "code": "JOD",
      "rate": 0.709,
      "name": "Jordanian Dinar"
    },
    {
      "code": "JPY",
      "rate": 162.4055,
      "name": "Japanese Yen"
    },
    {
      "code": "KES",
      "rate": 129.49,
      "name": "Kenyan Shilling"
    },
    {
      "code": "KGS",
      "rate": 87.45,
      "name": "Kyrgystani Som"
    },
    {
      "code": "KHR",
      "rate": 4025.82905,
      "name": "Cambodian Riel"
    },
    {
      "code": "KMF",
      "rate": 431.999741,
      "name": "Comorian Franc"
    },
    {
      "code": "KPW",
      "rate": 900,
      "name": "North Korean Won"
    },
    {
      "code": "KRW",
      "rate": 1550.42684,
      "name": "South Korean Won"
    },
    {
      "code": "KWD",
      "rate": 0.309756,
      "name": "Kuwaiti Dinar"
    },
    {
      "code": "KYD",
      "rate": 0.833593,
      "name": "Cayman Islands Dollar"
    },
    {
      "code": "KZT",
      "rate": 486.150588,
      "name": "Kazakhstani Tenge"
    },
    {
      "code": "LAK",
      "rate": 22433.948776,
      "name": "Laotian Kip"
    },
    {
      "code": "LBP",
      "rate": 89569.698885,
      "name": "Lebanese Pound"
    },
    {
      "code": "LKR",
      "rate": 336.09522,
      "name": "Sri Lankan Rupee"
    },
    {
      "code": "LRD",
      "rate": 181.58286,
      "name": "Liberian Dollar"
    },
    {
      "code": "LSL",
      "rate": 16.36882,
      "name": "Lesotho Loti"
    },
    {
      "code": "LYD",
      "rate": 6.42603,
      "name": "Libyan Dinar"
    },
    {
      "code": "MAD",
      "rate": 9.401556,
      "name": "Moroccan Dirham"
    },
    {
      "code": "MDL",
      "rate": 17.550109,
      "name": "Moldovan Leu"
    },
    {
      "code": "MGA",
      "rate": 4243.307509,
      "name": "Malagasy Ariary"
    },
    {
      "code": "MKD",
      "rate": 54.094021,
      "name": "Macedonian Denar"
    },
    {
      "code": "MMK",
      "rate": 2099.81,
      "name": "Myanma Kyat"
    },
    {
      "code": "MNT",
      "rate": 3569.47,
      "name": "Mongolian Tugrik"
    },
    {
      "code": "MOP",
      "rate": 8.08008,
      "name": "Macanese Pataca"
    },
    {
      "code": "MRU",
      "rate": 39.968069,
      "name": "Mauritanian Ouguiya"
    },
    {
      "code": "MUR",
      "rate": 47.190001,
      "name": "Mauritian Rupee"
    },
    {
      "code": "MVR",
      "rate": 15.46,
      "name": "Maldivian Rufiyaa"
    },
    {
      "code": "MWK",
      "rate": 1734.475136,
      "name": "Malawian Kwacha"
    },
    {
      "code": "MXN",
      "rate": 17.479127,
      "name": "Mexican Peso"
    },
    {
      "code": "MYR",
      "rate": 4.084,
      "name": "Malaysian Ringgit"
    },
    {
      "code": "MZN",
      "rate": 63.850001,
      "name": "Mozambican Metical"
    },
    {
      "code": "NAD",
      "rate": 16.369466,
      "name": "Namibian Dollar"
    },
    {
      "code": "NGN",
      "rate": 1381.58,
      "name": "Nigerian Naira"
    },
    {
      "code": "NIO",
      "rate": 36.809762,
      "name": "Nicaraguan Córdoba"
    },
    {
      "code": "NOK",
      "rate": 9.922906,
      "name": "Norwegian Krone"
    },
    {
      "code": "NPR",
      "rate": 151.417444,
      "name": "Nepalese Rupee"
    },
    {
      "code": "NZD",
      "rate": 1.766872,
      "name": "New Zealand Dollar"
    },
    {
      "code": "OMR",
      "rate": 0.3845,
      "name": "Omani Rial"
    },
    {
      "code": "PAB",
      "rate": 1,
      "name": "Panamanian Balboa"
    },
    {
      "code": "PEN",
      "rate": 3.418588,
      "name": "Peruvian Nuevo Sol"
    },
    {
      "code": "PGK",
      "rate": 4.393387,
      "name": "Papua New Guinean Kina"
    },
    {
      "code": "PHP",
      "rate": 61.382497,
      "name": "Philippine Peso"
    },
    {
      "code": "PKR",
      "rate": 278.141427,
      "name": "Pakistani Rupee"
    },
    {
      "code": "PLN",
      "rate": 3.769672,
      "name": "Polish Zloty"
    },
    {
      "code": "PYG",
      "rate": 6083.012919,
      "name": "Paraguayan Guarani"
    },
    {
      "code": "QAR",
      "rate": 3.656302,
      "name": "Qatari Rial"
    },
    {
      "code": "RON",
      "rate": 4.6007,
      "name": "Romanian Leu"
    },
    {
      "code": "RSD",
      "rate": 102.96842,
      "name": "Serbian Dinar"
    },
    {
      "code": "RUB",
      "rate": 78.504453,
      "name": "Russian Ruble"
    },
    {
      "code": "RWF",
      "rate": 1466.200387,
      "name": "Rwandan Franc"
    },
    {
      "code": "SAR",
      "rate": 3.751329,
      "name": "Saudi Riyal"
    },
    {
      "code": "SBD",
      "rate": 8.065041,
      "name": "Solomon Islands Dollar"
    },
    {
      "code": "SCR",
      "rate": 13.756823,
      "name": "Seychellois Rupee"
    },
    {
      "code": "SDG",
      "rate": 600.5,
      "name": "Sudanese Pound"
    },
    {
      "code": "SEK",
      "rate": 9.72782,
      "name": "Swedish Krona"
    },
    {
      "code": "SGD",
      "rate": 1.295003,
      "name": "Singapore Dollar"
    },
    {
      "code": "SHP",
      "rate": 0.756672,
      "name": "Saint Helena Pound"
    },
    {
      "code": "SLE",
      "rate": 22.9249,
      "name": "Sierra Leonean Leone"
    },
    {
      "code": "SLL",
      "rate": 20969.5,
      "name": "Sierra Leonean Leone (Old)"
    },
    {
      "code": "SOS",
      "rate": 571.631705,
      "name": "Somali Shilling"
    },
    {
      "code": "SRD",
      "rate": 37.4945,
      "name": "Surinamese Dollar"
    },
    {
      "code": "SSP",
      "rate": 130.26,
      "name": "South Sudanese Pound"
    },
    {
      "code": "STD",
      "rate": 22281.8,
      "name": "São Tomé and Príncipe Dobra (pre-2018)"
    },
    {
      "code": "STN",
      "rate": 21.492548,
      "name": "São Tomé and Príncipe Dobra"
    },
    {
      "code": "SVC",
      "rate": 8.752522,
      "name": "Salvadoran Colón"
    },
    {
      "code": "SYP",
      "rate": 13002,
      "name": "Syrian Pound"
    },
    {
      "code": "SZL",
      "rate": 16.447328,
      "name": "Swazi Lilangeni"
    },
    {
      "code": "THB",
      "rate": 33.2625,
      "name": "Thai Baht"
    },
    {
      "code": "TJS",
      "rate": 9.255533,
      "name": "Tajikistani Somoni"
    },
    {
      "code": "TMT",
      "rate": 3.51,
      "name": "Turkmenistani Manat"
    },
    {
      "code": "TND",
      "rate": 2.964392,
      "name": "Tunisian Dinar"
    },
    {
      "code": "TOP",
      "rate": 2.40776,
      "name": "Tongan Pa'anga"
    },
    {
      "code": "TRY",
      "rate": 46.659606,
      "name": "Turkish Lira"
    },
    {
      "code": "TTD",
      "rate": 6.789103,
      "name": "Trinidad and Tobago Dollar"
    },
    {
      "code": "TWD",
      "rate": 31.831401,
      "name": "New Taiwan Dollar"
    },
    {
      "code": "TZS",
      "rate": 2624.998,
      "name": "Tanzanian Shilling"
    },
    {
      "code": "UAH",
      "rate": 44.826939,
      "name": "Ukrainian Hryvnia"
    },
    {
      "code": "UGX",
      "rate": 3666.121053,
      "name": "Ugandan Shilling"
    },
    {
      "code": "USD",
      "rate": 1,
      "name": "United States Dollar"
    },
    {
      "code": "UYU",
      "rate": 40.150739,
      "name": "Uruguayan Peso"
    },
    {
      "code": "UZS",
      "rate": 12007.241453,
      "name": "Uzbekistan Som"
    },
    {
      "code": "VES",
      "rate": 622.24359,
      "name": "Venezuelan Bolívar Soberano"
    },
    {
      "code": "VND",
      "rate": 26312.327781,
      "name": "Vietnamese Dong"
    },
    {
      "code": "VUV",
      "rate": 119.389,
      "name": "Vanuatu Vatu"
    },
    {
      "code": "WST",
      "rate": 2.74422,
      "name": "Samoan Tala"
    },
    {
      "code": "YER",
      "rate": 238.600042,
      "name": "Yemeni Rial"
    },
    {
      "code": "ZAR",
      "rate": 16.394554,
      "name": "South African Rand"
    },
    {
      "code": "ZMW",
      "rate": 18.029889,
      "name": "Zambian Kwacha"
    },
    {
      "code": "ZWG",
      "rate": 25.3626,
      "name": "Zimbabwean ZiG"
    },
    {
      "code": "ZWL",
      "rate": 322,
      "name": "Zimbabwean Dollar"
    }
  ]
}
